poodigger/__init__.py
poodigger/parquet.py
poodigger-1.0.1.dist-info/licenses/LICENSE
poodigger-1.0.1.dist-info/METADATA
poodigger-1.0.1.dist-info/WHEEL
poodigger-1.0.1.dist-info/top_level.txt
poodigger-1.0.1.dist-info/RECORD
