Metadata-Version: 2.4
Name: poodigger
Version: 1.0.1
Summary: Blogger Comment Digging Toolkit
Home-page: https://github.com/asinerum/poodigger
Author: Asinerum Conlang Project
Author-email: asinerum.com@gmail.com
License: MIT
Classifier: Programming Language :: Python :: 3
Classifier: License :: OSI Approved :: MIT License
Classifier: Operating System :: OS Independent
Requires-Python: >=3.7
License-File: LICENSE
Requires-Dist: bs4>=0.0.2
Requires-Dist: duckdb>=1.4.2
Requires-Dist: formatize>=1.0.3
Requires-Dist: jinja2>=3.1.6
Requires-Dist: pandas>=2.3.3
Dynamic: license-file
